{
    "description": "",
    "tags": [
        {
            "id": 21823069,
            "tagId": 32241,
            "name": "sequence",
            "value": "Sequence1",
            "labelerLogin": "inbox@datasetninja.com",
            "createdAt": "2024-03-10T18:52:24.520Z",
            "updatedAt": "2024-03-10T18:52:24.520Z"
        },
        {
            "id": 21823070,
            "tagId": 32243,
            "name": "night",
            "value": null,
            "labelerLogin": "inbox@datasetninja.com",
            "createdAt": "2024-03-10T18:52:24.520Z",
            "updatedAt": "2024-03-10T18:52:24.520Z"
        },
        {
            "id": 21823071,
            "tagId": 32240,
            "name": "track frame number",
            "value": 2746,
            "labelerLogin": "inbox@datasetninja.com",
            "createdAt": "2024-03-10T18:52:24.520Z",
            "updatedAt": "2024-03-10T18:52:24.520Z"
        }
    ],
    "size": {
        "height": 960,
        "width": 1280
    },
    "objects": [
        {
            "id": 158682397,
            "classId": 6550272,
            "objectId": null,
            "description": "",
            "geometryType": "rectangle",
            "labelerLogin": "inbox@datasetninja.com",
            "createdAt": "2024-03-10T18:52:24.521Z",
            "updatedAt": "2024-03-10T18:52:24.521Z",
            "tags": [],
            "classTitle": "warning traffic light",
            "points": {
                "exterior": [
                    [
                        [
                            734,
                            456
                        ],
                        [
                            741,
                            468
                        ]
                    ]
                ],
                "interior": []
            }
        },
        {
            "id": 158682398,
            "classId": 6550272,
            "objectId": null,
            "description": "",
            "geometryType": "rectangle",
            "labelerLogin": "inbox@datasetninja.com",
            "createdAt": "2024-03-10T18:52:24.521Z",
            "updatedAt": "2024-03-10T18:52:24.521Z",
            "tags": [],
            "classTitle": "warning traffic light",
            "points": {
                "exterior": [
                    [
                        [
                            696,
                            436
                        ],
                        [
                            708,
                            464
                        ]
                    ]
                ],
                "interior": []
            }
        },
        {
            "id": 158682399,
            "classId": 6550270,
            "objectId": null,
            "description": "",
            "geometryType": "rectangle",
            "labelerLogin": "inbox@datasetninja.com",
            "createdAt": "2024-03-10T18:52:24.521Z",
            "updatedAt": "2024-03-10T18:52:24.521Z",
            "tags": [],
            "classTitle": "stop traffic light",
            "points": {
                "exterior": [
                    [
                        [
                            979,
                            364
                        ],
                        [
                            1016,
                            448
                        ]
                    ]
                ],
                "interior": []
            }
        },
        {
            "id": 158682400,
            "classId": 6550270,
            "objectId": null,
            "description": "",
            "geometryType": "rectangle",
            "labelerLogin": "inbox@datasetninja.com",
            "createdAt": "2024-03-10T18:52:24.521Z",
            "updatedAt": "2024-03-10T18:52:24.521Z",
            "tags": [],
            "classTitle": "stop traffic light",
            "points": {
                "exterior": [
                    [
                        [
                            620,
                            271
                        ],
                        [
                            657,
                            355
                        ]
                    ]
                ],
                "interior": []
            }
        },
        {
            "id": 158682401,
            "classId": 6550270,
            "objectId": null,
            "description": "",
            "geometryType": "rectangle",
            "labelerLogin": "inbox@datasetninja.com",
            "createdAt": "2024-03-10T18:52:24.522Z",
            "updatedAt": "2024-03-10T18:52:24.522Z",
            "tags": [],
            "classTitle": "stop traffic light",
            "points": {
                "exterior": [
                    [
                        [
                            750,
                            271
                        ],
                        [
                            787,
                            355
                        ]
                    ]
                ],
                "interior": []
            }
        },
        {
            "id": 158682402,
            "classId": 6550270,
            "objectId": null,
            "description": "",
            "geometryType": "rectangle",
            "labelerLogin": "inbox@datasetninja.com",
            "createdAt": "2024-03-10T18:52:24.522Z",
            "updatedAt": "2024-03-10T18:52:24.522Z",
            "tags": [],
            "classTitle": "stop traffic light",
            "points": {
                "exterior": [
                    [
                        [
                            543,
                            453
                        ],
                        [
                            549,
                            464
                        ]
                    ]
                ],
                "interior": []
            }
        },
        {
            "id": 158682403,
            "classId": 6550270,
            "objectId": null,
            "description": "",
            "geometryType": "rectangle",
            "labelerLogin": "inbox@datasetninja.com",
            "createdAt": "2024-03-10T18:52:24.522Z",
            "updatedAt": "2024-03-10T18:52:24.522Z",
            "tags": [],
            "classTitle": "stop traffic light",
            "points": {
                "exterior": [
                    [
                        [
                            705,
                            423
                        ],
                        [
                            718,
                            455
                        ]
                    ]
                ],
                "interior": []
            }
        },
        {
            "id": 158682404,
            "classId": 6550270,
            "objectId": null,
            "description": "",
            "geometryType": "rectangle",
            "labelerLogin": "inbox@datasetninja.com",
            "createdAt": "2024-03-10T18:52:24.522Z",
            "updatedAt": "2024-03-10T18:52:24.522Z",
            "tags": [],
            "classTitle": "stop traffic light",
            "points": {
                "exterior": [
                    [
                        [
                            759,
                            446
                        ],
                        [
                            774,
                            482
                        ]
                    ]
                ],
                "interior": []
            }
        }
    ]
}